souleyez/__init__.py
souleyez/config.py
souleyez/devtools.py
souleyez/feature_flags.py
souleyez/history.py
souleyez/log_config.py
souleyez/main.py
souleyez/scanner.py
souleyez/security.py
souleyez/ui.py
souleyez/utils.py
souleyez/wordlists.py
souleyez/ai/__init__.py
souleyez/ai/action_mapper.py
souleyez/ai/chain_advisor.py
souleyez/ai/claude_provider.py
souleyez/ai/context_builder.py
souleyez/ai/executor.py
souleyez/ai/feedback_handler.py
souleyez/ai/llm_factory.py
souleyez/ai/llm_provider.py
souleyez/ai/ollama_provider.py
souleyez/ai/ollama_service.py
souleyez/ai/path_scorer.py
souleyez/ai/recommender.py
souleyez/ai/report_context.py
souleyez/ai/report_prompts.py
souleyez/ai/report_service.py
souleyez/ai/result_parser.py
souleyez/ai/safety.py
souleyez/assets/__init__.py
souleyez/assets/souleyez-icon.png
souleyez/auth/__init__.py
souleyez/auth/audit.py
souleyez/auth/engagement_access.py
souleyez/auth/permissions.py
souleyez/auth/session_manager.py
souleyez/auth/user_manager.py
souleyez/commands/__init__.py
souleyez/commands/audit.py
souleyez/commands/auth.py
souleyez/commands/deliverables.py
souleyez/commands/engagement.py
souleyez/commands/license.py
souleyez/commands/screenshots.py
souleyez/commands/user.py
souleyez/core/__init__.py
souleyez/core/credential_tester.py
souleyez/core/cve_mappings.py
souleyez/core/cve_matcher.py
souleyez/core/msf_auto_mapper.py
souleyez/core/msf_chain_engine.py
souleyez/core/msf_database.py
souleyez/core/msf_integration.py
souleyez/core/msf_rpc_client.py
souleyez/core/msf_rpc_manager.py
souleyez/core/msf_sync_manager.py
souleyez/core/network_utils.py
souleyez/core/parser_handler.py
souleyez/core/pending_chains.py
souleyez/core/templates.py
souleyez/core/tool_chaining.py
souleyez/core/version_utils.py
souleyez/core/vuln_correlation.py
souleyez/core/web_utils.py
souleyez/data/templates/README.md
souleyez/data/templates/active_directory.json
souleyez/data/templates/cis_controls_v8.json
souleyez/data/templates/cloud_security.json
souleyez-3.0.11.dist-info/licenses/LICENSE
souleyez-3.0.11.dist-info/METADATA
souleyez-3.0.11.dist-info/WHEEL
souleyez-3.0.11.dist-info/entry_points.txt
souleyez-3.0.11.dist-info/top_level.txt
souleyez-3.0.11.dist-info/RECORD
