Metadata-Version: 2.4
Name: souleyez
Version: 3.0.11
Summary: AI-Powered Penetration Testing Platform with 40+ integrated tools
Author-email: CyberSoul Security <contact@cybersoulsecurity.com>
Maintainer-email: CyberSoul Security <contact@cybersoulsecurity.com>
License: MIT
Project-URL: Homepage, https://github.com/cyber-soul-security/SoulEyez
Project-URL: Documentation, https://github.com/cyber-soul-security/SoulEyez#readme
Project-URL: Repository, https://github.com/cyber-soul-security/SoulEyez.git
Project-URL: Issues, https://github.com/cyber-soul-security/SoulEyez/issues
Keywords: pentesting,security,hacking,penetration-testing,cybersecurity,nmap,metasploit
Classifier: Development Status :: 5 - Production/Stable
Classifier: Environment :: Console
Classifier: Environment :: Console :: Curses
Classifier: Intended Audience :: Developers
Classifier: Intended Audience :: Information Technology
Classifier: Intended Audience :: System Administrators
Classifier: License :: OSI Approved :: MIT License
Classifier: Operating System :: POSIX :: Linux
Classifier: Operating System :: MacOS
Classifier: Programming Language :: Python :: 3
Classifier: Programming Language :: Python :: 3.8
Classifier: Programming Language :: Python :: 3.9
Classifier: Programming Language :: Python :: 3.10
Classifier: Programming Language :: Python :: 3.11
Classifier: Programming Language :: Python :: 3.12
Classifier: Programming Language :: Python :: 3.13
Classifier: Topic :: Security
Classifier: Topic :: System :: Networking
Requires-Python: >=3.8
License-File: LICENSE
Requires-Dist: anthropic>=0.40.0
Requires-Dist: click>=8.0.0
Requires-Dist: cryptography>=3.4.0
Requires-Dist: defusedxml>=0.7.0
Requires-Dist: impacket>=0.11.0
Requires-Dist: markdown>=3.4.0
Requires-Dist: msgpack>=1.0.0
Requires-Dist: ollama>=0.1.0
Requires-Dist: psycopg2-binary>=2.9.0
Requires-Dist: psutil>=5.9.0
Requires-Dist: python-json-logger>=2.0.0
Requires-Dist: requests>=2.28.0
Requires-Dist: rich>=10.0.0
Requires-Dist: wcwidth>=0.2.0
Provides-Extra: dev
Requires-Dist: pytest>=7.0.0; extra == "dev"
Dynamic: license-file
